<annotation>
	<folder>20200829153758943.mp4_54</folder>
	<filename>img4.jpg</filename>
	<path>E:\dataset\C31\imgs_train\20200829153758943.mp4_54\img4.jpg</path>
	<source>
		<database>Unknown</database>
	</source>
	<size>
		<width>1920</width>
		<height>1080</height>
		<depth>3</depth>
	</size>
	<segmented>0</segmented>
	<object>
		<name>barrier</name>
		<pose>Unspecified</pose>
		<truncated>0</truncated>
		<difficult>0</difficult>
		<bndbox>
			<xmin>1327</xmin>
			<ymin>461</ymin>
			<xmax>1411</xmax>
			<ymax>568</ymax>
		</bndbox>
	</object>
	<object>
		<name>barrier</name>
		<pose>Unspecified</pose>
		<truncated>0</truncated>
		<difficult>0</difficult>
		<bndbox>
			<xmin>1612</xmin>
			<ymin>537</ymin>
			<xmax>1656</xmax>
			<ymax>583</ymax>
		</bndbox>
	</object>
	<object>
		<name>barrier</name>
		<pose>Unspecified</pose>
		<truncated>0</truncated>
		<difficult>0</difficult>
		<bndbox>
			<xmin>1683</xmin>
			<ymin>553</ymin>
			<xmax>1717</xmax>
			<ymax>573</ymax>
		</bndbox>
	</object>
</annotation>
