<annotation>
	<folder>20200829153758943.mp4_90</folder>
	<filename>img12.jpg</filename>
	<path>E:\dataset\C31\imgs_train\20200829153758943.mp4_90\img12.jpg</path>
	<source>
		<database>Unknown</database>
	</source>
	<size>
		<width>1920</width>
		<height>1080</height>
		<depth>3</depth>
	</size>
	<segmented>0</segmented>
	<object>
		<name>barrier</name>
		<pose>Unspecified</pose>
		<truncated>0</truncated>
		<difficult>0</difficult>
		<bndbox>
			<xmin>1407</xmin>
			<ymin>399</ymin>
			<xmax>1418</xmax>
			<ymax>414</ymax>
		</bndbox>
	</object>
	<object>
		<name>barrier</name>
		<pose>Unspecified</pose>
		<truncated>0</truncated>
		<difficult>0</difficult>
		<bndbox>
			<xmin>1428</xmin>
			<ymin>399</ymin>
			<xmax>1439</xmax>
			<ymax>416</ymax>
		</bndbox>
	</object>
	<object>
		<name>barrier</name>
		<pose>Unspecified</pose>
		<truncated>0</truncated>
		<difficult>0</difficult>
		<bndbox>
			<xmin>1204</xmin>
			<ymin>413</ymin>
			<xmax>1213</xmax>
			<ymax>427</ymax>
		</bndbox>
	</object>
	<object>
		<name>barrier</name>
		<pose>Unspecified</pose>
		<truncated>0</truncated>
		<difficult>0</difficult>
		<bndbox>
			<xmin>116</xmin>
			<ymin>485</ymin>
			<xmax>159</xmax>
			<ymax>512</ymax>
		</bndbox>
	</object>
	<object>
		<name>barrier</name>
		<pose>Unspecified</pose>
		<truncated>0</truncated>
		<difficult>0</difficult>
		<bndbox>
			<xmin>176</xmin>
			<ymin>471</ymin>
			<xmax>266</xmax>
			<ymax>510</ymax>
		</bndbox>
	</object>
</annotation>
