<annotation>
	<folder>20200829163250129_1.mp4_241</folder>
	<filename>img15.jpg</filename>
	<path>E:\2022SPR\C3\20200829163250129_1.mp4_241\img15.jpg</path>
	<source>
		<database>Unknown</database>
	</source>
	<size>
		<width>1920</width>
		<height>1080</height>
		<depth>3</depth>
	</size>
	<segmented>0</segmented>
	<object>
		<name>barrier</name>
		<pose>Unspecified</pose>
		<truncated>0</truncated>
		<difficult>0</difficult>
		<bndbox>
			<xmin>1615</xmin>
			<ymin>518</ymin>
			<xmax>1671</xmax>
			<ymax>549</ymax>
		</bndbox>
	</object>
	<object>
		<name>barrier</name>
		<pose>Unspecified</pose>
		<truncated>0</truncated>
		<difficult>0</difficult>
		<bndbox>
			<xmin>1516</xmin>
			<ymin>536</ymin>
			<xmax>1548</xmax>
			<ymax>562</ymax>
		</bndbox>
	</object>
	<object>
		<name>barrier</name>
		<pose>Unspecified</pose>
		<truncated>0</truncated>
		<difficult>0</difficult>
		<bndbox>
			<xmin>1309</xmin>
			<ymin>516</ymin>
			<xmax>1424</xmax>
			<ymax>557</ymax>
		</bndbox>
	</object>
	<object>
		<name>barrier</name>
		<pose>Unspecified</pose>
		<truncated>0</truncated>
		<difficult>0</difficult>
		<bndbox>
			<xmin>409</xmin>
			<ymin>581</ymin>
			<xmax>434</xmax>
			<ymax>592</ymax>
		</bndbox>
	</object>
	<object>
		<name>coast</name>
		<pose>Unspecified</pose>
		<truncated>1</truncated>
		<difficult>0</difficult>
		<bndbox>
			<xmin>5</xmin>
			<ymin>96</ymin>
			<xmax>1920</xmax>
			<ymax>602</ymax>
		</bndbox>
	</object>
	<object>
		<name>barrier</name>
		<pose>Unspecified</pose>
		<truncated>0</truncated>
		<difficult>0</difficult>
		<bndbox>
			<xmin>21</xmin>
			<ymin>584</ymin>
			<xmax>37</xmax>
			<ymax>608</ymax>
		</bndbox>
	</object>
</annotation>
