<annotation>
	<folder>20200829163250129_1.mp4_241</folder>
	<filename>img50.jpg</filename>
	<path>E:\2022SPR\C3\20200829163250129_1.mp4_241\img50.jpg</path>
	<source>
		<database>Unknown</database>
	</source>
	<size>
		<width>1920</width>
		<height>1080</height>
		<depth>3</depth>
	</size>
	<segmented>0</segmented>
	<object>
		<name>coast</name>
		<pose>Unspecified</pose>
		<truncated>1</truncated>
		<difficult>0</difficult>
		<bndbox>
			<xmin>1</xmin>
			<ymin>138</ymin>
			<xmax>1920</xmax>
			<ymax>597</ymax>
		</bndbox>
	</object>
	<object>
		<name>barrier</name>
		<pose>Unspecified</pose>
		<truncated>0</truncated>
		<difficult>0</difficult>
		<bndbox>
			<xmin>367</xmin>
			<ymin>583</ymin>
			<xmax>396</xmax>
			<ymax>600</ymax>
		</bndbox>
	</object>
	<object>
		<name>barrier</name>
		<pose>Unspecified</pose>
		<truncated>0</truncated>
		<difficult>0</difficult>
		<bndbox>
			<xmin>1308</xmin>
			<ymin>555</ymin>
			<xmax>1420</xmax>
			<ymax>596</ymax>
		</bndbox>
	</object>
	<object>
		<name>barrier</name>
		<pose>Unspecified</pose>
		<truncated>0</truncated>
		<difficult>0</difficult>
		<bndbox>
			<xmin>1520</xmin>
			<ymin>588</ymin>
			<xmax>1569</xmax>
			<ymax>618</ymax>
		</bndbox>
	</object>
	<object>
		<name>barrier</name>
		<pose>Unspecified</pose>
		<truncated>0</truncated>
		<difficult>0</difficult>
		<bndbox>
			<xmin>1611</xmin>
			<ymin>566</ymin>
			<xmax>1658</xmax>
			<ymax>602</ymax>
		</bndbox>
	</object>
</annotation>
